PL94andTigertoSQLite3/PL94andTigertoSQLite3.py
PL94andTigertoSQLite3/__init__.py
PL94andTigertoSQLite3/__main__.py
PL94andTigertoSQLite3/cli.py
PL94andTigertoSQLite3-0.1.1.dist-info/LICENSE.txt
PL94andTigertoSQLite3-0.1.1.dist-info/METADATA
PL94andTigertoSQLite3-0.1.1.dist-info/WHEEL
PL94andTigertoSQLite3-0.1.1.dist-info/top_level.txt
PL94andTigertoSQLite3-0.1.1.dist-info/RECORD
